datasetool/__init__.py
datasetool/cli.py
datasetool/exceptions.py
datasetool/split.py
datasetool-0.1.2.dist-info/licenses/LICENSE
datasetool-0.1.2.dist-info/METADATA
datasetool-0.1.2.dist-info/WHEEL
datasetool-0.1.2.dist-info/entry_points.txt
datasetool-0.1.2.dist-info/top_level.txt
datasetool-0.1.2.dist-info/RECORD
