Metadata-Version: 2.4
Name: datasetool
Version: 0.1.2
Summary: A tiny yet robust dataset split tool for YOLO-style datasets
Author-email: mozihe <zhujunheng2005@gmail.com>
License: MIT
Project-URL: Homepage, https://github.com/mozihe/datasetool
Project-URL: Issues, https://github.com/mozihe/datasetool/issues
Keywords: dataset,yolo,split,computer-vision,ml
Classifier: Programming Language :: Python :: 3
Classifier: License :: OSI Approved :: MIT License
Classifier: Operating System :: OS Independent
Classifier: Topic :: Scientific/Engineering :: Artificial Intelligence
Classifier: Environment :: Console
Requires-Python: >=3.8
License-File: LICENSE
Provides-Extra: progress
Requires-Dist: tqdm>=4.66; extra == "progress"
Dynamic: license-file
